coloredconsole/__init__.py
coloredconsole-0.0.2.dist-info/WHEEL
coloredconsole-0.0.2.dist-info/METADATA
coloredconsole-0.0.2.dist-info/RECORD
